setup.py
negotiate/__init__.py
negotiate/compat.py
negotiate/flask.py
negotiate/pylons.py
negotiate.egg-info/PKG-INFO
negotiate.egg-info/SOURCES.txt
negotiate.egg-info/dependency_links.txt
negotiate.egg-info/requires.txt
negotiate.egg-info/top_level.txt
tests/__init__.py
tests/helpers.py
tests/test_negotiate.py