Metadata-Version: 1.0
Name: negotiate
Version: 0.0.1
Summary: Negotiate: smart, simple content negotiation for Python web applications
Home-page: https://github.com/nickstenning/negotiate
Author: Nick Stenning
Author-email: nick@whiteink.com
License: MIT
Keywords: contenttype contentnegotiation http hypermedia
Platform: UNKNOWN
